{
    "boxShadow": "none",
    "mobileBottomRow": 31,
    "widgetName": "fpk_selectImage",
    "buttonColor": "{{appsmith.theme.colors.primaryColor}}",
    "displayName": "FilePicker",
    "iconSVG": "https://appcdn.appsmith.com/static/media/icon.715769b31db833b32f40d9c90ec02de3.svg",
    "searchTags": ["upload"],
    "topRow": 4,
    "bottomRow": 9,
    "parentRowSpace": 10,
    "type": "FILE_PICKER_WIDGET_V2",
    "allowedFileTypes": ["image/*"],
    "hideCard": false,
    "mobileRightColumn": 16,
    "animateLoading": true,
    "parentColumnSpace": 8.6650390625,
    "dynamicTriggerPathList": [{"key": "onFilesSelected"}],
    "leftColumn": 0,
    "dynamicBindingPathList": [
        {"key": "borderRadius"},
        {"key": "buttonColor"}
    ],
    "isDisabled": false,
    "key": "5azr302uj1",
    "onFilesSelected": "",
    "isRequired": false,
    "isDeprecated": false,
    "rightColumn": 64,
    "isDefaultClickDisabled": true,
    "widgetId": "luh1nrsz9x",
    "minWidth": 120,
    "isVisible": true,
    "label": "Select Image",
    "maxFileSize": 5,
    "dynamicTyping": true,
    "version": 1,
    "fileDataType": "Base64",
    "parentId": "0bw2f7zunw",
    "tags": ["Inputs"],
    "selectedFiles": [],
    "renderMode": "CANVAS",
    "isLoading": false,
    "mobileTopRow": 27,
    "responsiveBehavior": "hug",
    "originalTopRow": 4,
    "borderRadius": "{{appsmith.theme.borderRadius.appBorderRadius}}",
    "mobileLeftColumn": 0,
    "originalBottomRow": 9,
    "files": [],
    "maxNumFiles": 1
}